kick-i18ndude.sh
setup.cfg
setup.py
jyu/__init__.py
jyu.rsslisting.egg-info/PKG-INFO
jyu.rsslisting.egg-info/SOURCES.txt
jyu.rsslisting.egg-info/dependency_links.txt
jyu.rsslisting.egg-info/entry_points.txt
jyu.rsslisting.egg-info/namespace_packages.txt
jyu.rsslisting.egg-info/not-zip-safe
jyu.rsslisting.egg-info/paster_plugins.txt
jyu.rsslisting.egg-info/requires.txt
jyu.rsslisting.egg-info/top_level.txt
jyu/rsslisting/README.txt
jyu/rsslisting/__init__.py
jyu/rsslisting/config.py
jyu/rsslisting/configure.zcml
jyu/rsslisting/version.txt
jyu/rsslisting/browser/__init__.py
jyu/rsslisting/browser/configure.zcml
jyu/rsslisting/browser/rsslisting.py
jyu/rsslisting/browser/rsslisting_boxview.pt
jyu/rsslisting/browser/rsslisting_view.pt
jyu/rsslisting/browser/images/rsslisting_icon.gif
jyu/rsslisting/browser/styles/rsslisting.css
jyu/rsslisting/content/__init__.py
jyu/rsslisting/content/configure.zcml
jyu/rsslisting/content/rsslisting.py
jyu/rsslisting/i18n/plone-fi.po
jyu/rsslisting/i18n/plone.pot
jyu/rsslisting/interfaces/__init__.py
jyu/rsslisting/interfaces/rsslisting.py
jyu/rsslisting/locales/jyu.rsslisting.pot
jyu/rsslisting/locales/fi/LC_MESSAGES/jyu.rsslisting.po
jyu/rsslisting/profiles/default/cssregistry.xml
jyu/rsslisting/profiles/default/factorytool.xml
jyu/rsslisting/profiles/default/metadata.xml
jyu/rsslisting/profiles/default/types.xml
jyu/rsslisting/profiles/default/types/RSS_Listing.xml
jyu/rsslisting/tests/__init__.py
jyu/rsslisting/tests/base.py
jyu/rsslisting/tests/test_doctest.py
jyu/rsslisting/tests/test_rsslisting.py