Metadata-Version: 1.0
Name: jyu.rsslisting
Version: 1.0.1
Summary: A page, which displays an RSS feeds (or aggregation of several feeds) in the same way as RSS portlet does
Home-page: http://svn.plone.org/svn/collective/jyu.rsslisting
Author: Jukka Ojaniemi
Author-email: jukka.ojaniemi@jyu.fi
License: GPL
Keywords: plone rss listing view
Platform: UNKNOWN
Classifier: Framework :: Plone
Classifier: Intended Audience :: Developers
Classifier: Topic :: Software Development :: Libraries :: Python Modules
Classifier: License :: OSI Approved :: GNU General Public License (GPL)
